{
    "housePlaces": [
        {"ingles": "kitchen", "español": "cocina"},
        {"ingles": "living room", "español": "sala de estar"},
        {"ingles": "bedroom", "español": "dormitorio"},
        {"ingles": "bathroom", "español": "baño"},
        {"ingles": "dining room", "español": "comedor"},
        {"ingles": "office", "español": "oficina"},
        {"ingles": "laundry room", "español": "lavandería"},
        {"ingles": "garage", "español": "garaje"},
        {"ingles": "patio", "español": "patio"},
        {"ingles": "garden", "español": "jardín"},
        {"ingles": "balcony", "español": "balcón"},
        {"ingles": "attic", "español": "ático"},
        {"ingles": "basement", "español": "sótano"},
        {"ingles": "staircase", "español": "escalera"},
        {"ingles": "hallway", "español": "pasillo"},
        {"ingles": "playroom", "español": "sala de juegos"},
        {"ingles": "library", "español": "biblioteca"},
        {"ingles": "study", "español": "estudio"}
    ],
    "kitchenItems": [
        {"ingles": "knife", "español": "cuchillo"},
        {"ingles": "spoon", "español": "cuchara"},
        {"ingles": "fork", "español": "tenedor"},
        {"ingles": "plate", "español": "plato"},
        {"ingles": "bowl", "español": "tazón"},
        {"ingles": "glass", "español": "vaso"},
        {"ingles": "pan", "español": "sartén"},
        {"ingles": "pot", "español": "olla"},
        {"ingles": "cutting board", "español": "tabla de cortar"},
        {"ingles": "measuring cup", "español": "taza medidora"},
        {"ingles": "mixing bowl", "español": "recipiente para mezclar"},
        {"ingles": "whisk", "español": "batidor"},
        {"ingles": "spatula", "español": "espátula"},
        {"ingles": "grater", "español": "rallador"},
        {"ingles": "peeler", "español": "pelador"},
        {"ingles": "colander", "español": "colador"},
        {"ingles": "tongs", "español": "pinzas"},
        {"ingles": "oven mitts", "español": "guantes de horno"},
        {"ingles": "can opener", "español": "abrelatas"},
        {"ingles": "blender", "español": "licuadora"},
        {"ingles": "stove", "español": "estufa"},
        {"ingles": "oven", "español": "horno"},
        {"ingles": "refrigerator", "español": "refrigerador"},
        {"ingles": "microwave", "español": "microondas"},
        {"ingles": "toaster", "español": "tostadora"},
        {"ingles": "coffee maker", "español": "cafetera"},
        {"ingles": "electric kettle", "español": "hervidor eléctrico"},
        {"ingles": "food processor", "español": "procesador de alimentos"},
        {"ingles": "juicer", "español": "exprimidor"}
    ],
    "animales": [
        {"ingles": "dog", "español": "perro"},
        {"ingles": "cat", "español": "gato"},
        {"ingles": "elephant", "español": "elefante"},
        {"ingles": "lion", "español": "león"},
        {"ingles": "tiger", "español": "tigre"},
        {"ingles": "giraffe", "español": "jirafa"},
        {"ingles": "monkey", "español": "mono"},
        {"ingles": "zebra", "español": "cebra"},
        {"ingles": "hippopotamus", "español": "hipopótamo"},
        {"ingles": "koala", "español": "koala"},
        {"ingles": "penguin", "español": "pingüino"},
        {"ingles": "rhinoceros", "español": "rinoceronte"},
        {"ingles": "crocodile", "español": "cocodrilo"},
        {"ingles": "parrot", "español": "loro"},
        {"ingles": "dolphin", "español": "delfín"},
        {"ingles": "panda", "español": "panda"},
        {"ingles": "cheetah", "español": "guepardo"},
        {"ingles": "hedgehog", "español": "erizo"},
        {"ingles": "bear", "español": "oso"},
        {"ingles": "wolf", "español": "lobo"},
        {"ingles": "rabbit", "español": "conejo"},
        {"ingles": "deer", "español": "ciervo"},
        {"ingles": "seal", "español": "foca"},
        {"ingles": "gorilla", "español": "gorila"},
        {"ingles": "camel", "español": "camello"},
        {"ingles": "otter", "español": "nutria"},
        {"ingles": "turtle", "español": "tortuga"},
        {"ingles": "flamingo", "español": "flamenco"},
        {"ingles": "whale", "español": "ballena"},
        {"ingles": "shark", "español": "tiburón"},
        {"ingles": "penguin", "español": "pingüino"},
        {"ingles": "octopus", "español": "pulpo"},
        {"ingles": "eagle", "español": "águila"},
        {"ingles": "snake", "español": "serpiente"},
        {"ingles": "bat", "español": "murciélago"},
        {"ingles": "owl", "español": "búho"},
        {"ingles": "dolphin", "español": "delfín"},
        {"ingles": "polar bear", "español": "oso polar"},
        {"ingles": "camel", "español": "camello"},
        {"ingles": "panda", "español": "panda"},
        {"ingles": "chimpanzee", "español": "chimpancé"},
        {"ingles": "peacock", "español": "pavo real"},
        {"ingles": "giraffe", "español": "jirafa"},
        {"ingles": "elephant", "español": "elefante"},
        {"ingles": "koala", "español": "koala"},
        {"ingles": "crocodile", "español": "cocodrilo"},
        {"ingles": "gorilla", "español": "gorila"},
        {"ingles": "hippopotamus", "español": "hipopótamo"},
        {"ingles": "cheetah", "español": "guepardo"},
        {"ingles": "rabbit", "español": "conejo"},
        {"ingles": "seal", "español": "foca"},
        {"ingles": "rhinoceros", "español": "rinoceronte"},
        {"ingles": "parrot", "español": "loro"},
        {"ingles": "wolf", "español": "lobo"},
        {"ingles": "snake", "español": "serpiente"},
        {"ingles": "toucan", "español": "tucán"},
        {"ingles": "jaguar", "español": "jaguar"},
        {"ingles": "penguin", "español": "pingüino"},
        {"ingles": "flamingo", "español": "flamenco"},
        {"ingles": "turtle", "español": "tortuga"},
        {"ingles": "hedgehog", "español": "erizo"},
        {"ingles": "whale", "español": "ballena"},
        {"ingles": "shark", "español": "tiburón"},
        {"ingles": "otter", "español": "nutria"},
        {"ingles": "bat", "español": "murciélago"},
        {"ingles": "owl", "español": "búho"},
        {"ingles": "eagle", "español": "águila"},
        {"ingles": "polar bear", "español": "oso polar"},
        {"ingles": "chimpanzee", "español": "chimpancé"}
    ],
    "fruitsAndVegetables": [
        { "ingles": "apple", "español": "manzana" },
        { "ingles": "banana", "español": "plátano" },
        { "ingles": "orange", "español": "naranja" },
        { "ingles": "strawberry", "español": "fresa" },
        { "ingles": "grape", "español": "uva" },
        { "ingles": "watermelon", "español": "sandía" },
        { "ingles": "pineapple", "español": "piña" },
        { "ingles": "kiwi", "español": "kiwi" },
        { "ingles": "mango", "español": "mango" },
        { "ingles": "pear", "español": "pera" },
        { "ingles": "peach", "español": "durazno" },
        { "ingles": "cherry", "español": "cereza" },
        { "ingles": "plum", "español": "ciruela" },
        { "ingles": "avocado", "español": "aguacate" },
        { "ingles": "tomato", "español": "tomate" },
        { "ingles": "carrot", "español": "zanahoria" },
        { "ingles": "broccoli", "español": "brócoli" },
        { "ingles": "cabbage", "español": "repollo" },
        { "ingles": "spinach", "español": "espinaca" },
        { "ingles": "lettuce", "español": "lechuga" },
        { "ingles": "potato", "español": "papa" },
        { "ingles": "onion", "español": "cebolla" },
        { "ingles": "garlic", "español": "ajo" },
        { "ingles": "pepper", "español": "pimiento" },
        { "ingles": "cucumber", "español": "pepino" },
        { "ingles": "zucchini", "español": "calabacín" },
        { "ingles": "eggplant", "español": "berenjena" },
        { "ingles": "corn", "español": "maíz" },
        { "ingles": "green bean", "español": "ejote" },
        { "ingles": "asparagus", "español": "espárrago" },
        { "ingles": "pea", "español": "guisante" },
        { "ingles": "artichoke", "español": "alcachofa" },
        { "ingles": "cauliflower", "español": "coliflor" },
        { "ingles": "celery", "español": "apio" },
        { "ingles": "radish", "español": "rábano" },
        { "ingles": "beetroot", "español": "remolacha" },
        { "ingles": "pumpkin", "español": "calabaza" },
        { "ingles": "lemon", "español": "limón" },
        { "ingles": "lime", "español": "lima" },
        { "ingles": "coconut", "español": "coco" },
        { "ingles": "pomegranate", "español": "granada" },
        { "ingles": "melon", "español": "melón" },
        { "ingles": "blueberry", "español": "arándano" },
        { "ingles": "raspberry", "español": "frambuesa" },
        { "ingles": "blackberry", "español": "zarzamora" },
        { "ingles": "cranberry", "español": "arándano rojo" },
        { "ingles": "fig", "español": "higo" },
        { "ingles": "apricot", "español": "albaricoque" },
        { "ingles": "guava", "español": "guayaba" },
        { "ingles": "persimmon", "español": "caqui" },
        { "ingles": "date", "español": "dátil" },
        { "ingles": "passion fruit", "español": "maracuyá" }
    ],
    "professions": [
        { "ingles": "doctor", "español": "médico" },
        { "ingles": "teacher", "español": "maestro" },
        { "ingles": "engineer", "español": "ingeniero" },
        { "ingles": "lawyer", "español": "abogado" },
        { "ingles": "nurse", "español": "enfermero" },
        { "ingles": "architect", "español": "arquitecto" },
        { "ingles": "police officer", "español": "oficial de policía" },
        { "ingles": "firefighter", "español": "bombero" },
        { "ingles": "pilot", "español": "piloto" },
        { "ingles": "veterinarian", "español": "veterinario" },
        { "ingles": "dentist", "español": "dentista" },
        { "ingles": "accountant", "español": "contador" },
        { "ingles": "artist", "español": "artista" },
        { "ingles": "writer", "español": "escritor" },
        { "ingles": "musician", "español": "músico" },
        { "ingles": "actor", "español": "actor" },
        { "ingles": "athlete", "español": "atleta" },
        { "ingles": "scientist", "español": "científico" },
        { "ingles": "journalist", "español": "periodista" },
        { "ingles": "mechanic", "español": "mecánico" },
        { "ingles": "electrician", "español": "electricista" },
        { "ingles": "plumber", "español": "fontanero" },
        { "ingles": "fashion designer", "español": "diseñador de moda" },
        { "ingles": "photographer", "español": "fotógrafo" },
        { "ingles": "salesperson", "español": "vendedor" },
        { "ingles": "translator", "español": "traductor" },
        { "ingles": "consultant", "español": "consultor" },
        { "ingles": "psychologist", "español": "psicólogo" },
        { "ingles": "social worker", "español": "trabajador social" },
        { "ingles": "hairdresser", "español": "peluquero" },
        { "ingles": "gardener", "español": "jardinero" },
        { "ingles": "waiter/waitress", "español": "mesero/mesera" },
        { "ingles": "banker", "español": "banquero" },
        { "ingles": "chemist", "español": "químico" },
        { "ingles": "pharmacist", "español": "farmacéutico" },
        { "ingles": "judge", "español": "juez" },
        { "ingles": "politician", "español": "político" },
        { "ingles": "entrepreneur", "español": "empresario" },
        { "ingles": "policeman", "español": "policía" },
        { "ingles": "detective", "español": "detective" },
        { "ingles": "scientist", "español": "científico" },
        { "ingles": "surgeon", "español": "cirujano" },
        { "ingles": "astronomer", "español": "astrónomo" },
        { "ingles": "geologist", "español": "geólogo" },
        { "ingles": "chemist", "español": "químico" },
        { "ingles": "pharmacist", "español": "farmacéutico" },
        { "ingles": "athlete", "español": "atleta" },
        { "ingles": "researcher", "español": "investigador" },
        { "ingles": "veterinary technician", "español": "técnico veterinario" },
        { "ingles": "electrician", "español": "electricista" },
        { "ingles": "plumber", "español": "fontanero" },
        { "ingles": "music teacher", "español": "profesor de música" },
        { "ingles": "pianist", "español": "pianista" },
        { "ingles": "mathematician", "español": "matemático" },
        { "ingles": "singer", "español": "cantante" },
        { "ingles": "sculptor", "español": "escultor" }
    ],
    "sports": [
        { "ingles": "soccer", "español": "fútbol" },
        { "ingles": "football", "español": "fútbol americano" },
        { "ingles": "basketball", "español": "baloncesto" },
        { "ingles": "tennis", "español": "tenis" },
        { "ingles": "swimming", "español": "natación" },
        { "ingles": "volleyball", "español": "voleibol" },
        { "ingles": "baseball", "español": "béisbol" },
        { "ingles": "golf", "español": "golf" },
        { "ingles": "hockey", "español": "hockey" },
        { "ingles": "cricket", "español": "cricket" },
        { "ingles": "rugby", "español": "rugby" },
        { "ingles": "athletics", "español": "atletismo" },
        { "ingles": "cycling", "español": "ciclismo" },
        { "ingles": "boxing", "español": "boxeo" },
        { "ingles": "skiing", "español": "esquí" },
        { "ingles": "snowboarding", "español": "snowboarding" },
        { "ingles": "surfing", "español": "surf" },
        { "ingles": "wrestling", "español": "lucha libre" },
        { "ingles": "karate", "español": "karate" },
        { "ingles": "taekwondo", "español": "taekwondo" },
        { "ingles": "judo", "español": "judo" },
        { "ingles": "table tennis", "español": "tenis de mesa" },
        { "ingles": "badminton", "español": "bádminton" },
        { "ingles": "gymnastics", "español": "gimnasia" },
        { "ingles": "archery", "español": "tiro con arco" },
        { "ingles": "sailing", "español": "navegación a vela" },
        { "ingles": "canoeing", "español": "piragüismo" },
        { "ingles": "kayaking", "español": "kayak" },
        { "ingles": "rowing", "español": "remo" },
        { "ingles": "weightlifting", "español": "halterofilia" },
        { "ingles": "fencing", "español": "esgrima" },
        { "ingles": "shooting", "español": "tiro deportivo" },
        { "ingles": "climbing", "español": "escalada" },
        { "ingles": "handball", "español": "balonmano" },
        { "ingles": "bobsleigh", "español": "bobsleigh" },
        { "ingles": "luge", "español": "luge" },
        { "ingles": "skateboarding", "español": "skateboarding" },
        { "ingles": "paragliding", "español": "parapente" },
        { "ingles": "hiking", "español": "senderismo" },
        { "ingles": "yoga", "español": "yoga" },
        { "ingles": "pilates", "español": "pilates" },
        { "ingles": "parkour", "español": "parkour" },
        { "ingles": "trampolining", "español": "trampolín" },
        { "ingles": "roller skating", "español": "patinaje sobre ruedas" },
        { "ingles": "ice skating", "español": "patinaje sobre hielo" },
        { "ingles": "polo", "español": "polo" },
        { "ingles": "motor racing", "español": "automovilismo" },
        { "ingles": "synchronized swimming", "español": "natación sincronizada" },
        { "ingles": "triathlon", "español": "triatlón" }
    ],
    "colors": [
        { "ingles": "red", "español": "rojo" },
        { "ingles": "blue", "español": "azul" },
        { "ingles": "green", "español": "verde" },
        { "ingles": "yellow", "español": "amarillo" },
        { "ingles": "orange", "español": "naranja" },
        { "ingles": "purple", "español": "morado" },
        { "ingles": "pink", "español": "rosa" },
        { "ingles": "black", "español": "negro" },
        { "ingles": "white", "español": "blanco" },
        { "ingles": "gray", "español": "gris" },
        { "ingles": "brown", "español": "marrón" },
        { "ingles": "teal", "español": "verde azulado" },
        { "ingles": "navy", "español": "azul marino" },
        { "ingles": "magenta", "español": "magenta" },
        { "ingles": "turquoise", "español": "turquesa" },
        { "ingles": "lime", "español": "lima" },
        { "ingles": "gold", "español": "dorado" },
        { "ingles": "silver", "español": "plateado" },
        { "ingles": "maroon", "español": "granate" },
        { "ingles": "olive", "español": "oliva" },
        { "ingles": "indigo", "español": "añil" },
        { "ingles": "violet", "español": "violeta" },
        { "ingles": "cyan", "español": "cian" },
        { "ingles": "salmon", "español": "salmón" },
        { "ingles": "beige", "español": "beige" },
        { "ingles": "coral", "español": "coral" },
        { "ingles": "lavender", "español": "lavanda" },
        { "ingles": "orchid", "español": "orquídea" },
        { "ingles": "khaki", "español": "caqui" }
    ],
    "countries": [
        { "ingles": "Afghanistan", "español": "Afganistán" },
        { "ingles": "Albania", "español": "Albania" },
        { "ingles": "Algeria", "español": "Argelia" },
        { "ingles": "Andorra", "español": "Andorra" },
        { "ingles": "Angola", "español": "Angola" },
        { "ingles": "Antigua and Barbuda", "español": "Antigua y Barbuda" },
        { "ingles": "Argentina", "español": "Argentina" },
        { "ingles": "Armenia", "español": "Armenia" },
        { "ingles": "Australia", "español": "Australia" },
        { "ingles": "Austria", "español": "Austria" },
        { "ingles": "Azerbaijan", "español": "Azerbaiyán" },
        { "ingles": "Bahamas", "español": "Bahamas" },
        { "ingles": "Bahrain", "español": "Bahrein" },
        { "ingles": "Bangladesh", "español": "Bangladesh" },
        { "ingles": "Barbados", "español": "Barbados" },
        { "ingles": "Belarus", "español": "Bielorrusia" },
        { "ingles": "Belgium", "español": "Bélgica" },
        { "ingles": "Belize", "español": "Belice" },
        { "ingles": "Benin", "español": "Benin" },
        { "ingles": "Bhutan", "español": "Bután" },
        { "ingles": "Bolivia", "español": "Bolivia" },
        { "ingles": "Bosnia and Herzegovina", "español": "Bosnia y Herzegovina" },
        { "ingles": "Botswana", "español": "Botswana" },
        { "ingles": "Brazil", "español": "Brasil" },
        { "ingles": "Brunei", "español": "Brunéi" },
        { "ingles": "Bulgaria", "español": "Bulgaria" },
        { "ingles": "Burkina Faso", "español": "Burkina Faso" },
        { "ingles": "Burundi", "español": "Burundi" },
        { "ingles": "Cabo Verde", "español": "Cabo Verde" },
        { "ingles": "Cambodia", "español": "Camboya" },
        { "ingles": "Cameroon", "español": "Camerún" },
        { "ingles": "Canada", "español": "Canadá" },
        { "ingles": "Central African Republic", "español": "República Centroafricana" },
        { "ingles": "Chad", "español": "Chad" },
        { "ingles": "Chile", "español": "Chile" },
        { "ingles": "China", "español": "China" },
        { "ingles": "Colombia", "español": "Colombia" },
        { "ingles": "Comoros", "español": "Comoras" },
        { "ingles": "Congo", "español": "Congo" },
        { "ingles": "Costa Rica", "español": "Costa Rica" },
        { "ingles": "Croatia", "español": "Croacia" },
        { "ingles": "Cuba", "español": "Cuba" },
        { "ingles": "Cyprus", "español": "Chipre" },
        { "ingles": "Czech Republic", "español": "República Checa" },
        { "ingles": "Denmark", "español": "Dinamarca" },
        { "ingles": "Djibouti", "español": "Djibouti" },
        { "ingles": "Dominica", "español": "Dominica" },
        { "ingles": "Dominican Republic", "español": "República Dominicana" },
        { "ingles": "East Timor", "español": "Timor Oriental" },
        { "ingles": "Ecuador", "español": "Ecuador" },
        { "ingles": "Egypt", "español": "Egipto" },
        { "ingles": "El Salvador", "español": "El Salvador" },
        { "ingles": "Equatorial Guinea", "español": "Guinea Ecuatorial" },
        { "ingles": "Eritrea", "español": "Eritrea" },
        { "ingles": "Estonia", "español": "Estonia" },
        { "ingles": "Ethiopia", "español": "Etiopía" },
        { "ingles": "Fiji", "español": "Fiyi" },
        { "ingles": "Finland", "español": "Finlandia" },
        { "ingles": "France", "español": "Francia" },
        { "ingles": "Gabon", "español": "Gabón" },
        { "ingles": "Gambia", "español": "Gambia" },
        { "ingles": "Georgia", "español": "Georgia" },
        { "ingles": "Germany", "español": "Alemania" },
        { "ingles": "Ghana", "español": "Ghana" },
        { "ingles": "Greece", "español": "Grecia" },
        { "ingles": "Grenada", "español": "Granada" },
        { "ingles": "Guatemala", "español": "Guatemala" },
        { "ingles": "Guinea", "español": "Guinea" },
        { "ingles": "Guinea-Bissau", "español": "Guinea-Bisáu" },
        { "ingles": "Guyana", "español": "Guyana" },
        { "ingles": "Haiti", "español": "Haití" },
        { "ingles": "Honduras", "español": "Honduras" },
        { "ingles": "Hungary", "español": "Hungría" },
        { "ingles": "Iceland", "español": "Islandia" },
        { "ingles": "India", "español": "India" },
        { "ingles": "Indonesia", "español": "Indonesia" },
        { "ingles": "Iran", "español": "Irán" },
        { "ingles": "Iraq", "español": "Irak" },
        { "ingles": "Ireland", "español": "Irlanda" },
        { "ingles": "Israel", "español": "Israel" },
        { "ingles": "Italy", "español": "Italia" },
        { "ingles": "Jamaica", "español": "Jamaica" },
        { "ingles": "Japan", "español": "Japón" },
        { "ingles": "Jordan", "español": "Jordania" },
        { "ingles": "Kazakhstan", "español": "Kazajstán" },
        { "ingles": "Kenya", "español": "Kenia" },
        { "ingles": "Kiribati", "español": "Kiribati" },
        { "ingles": "Korea, North", "español": "Corea del Norte" },
        { "ingles": "Korea, South", "español": "Corea del Sur" },
        { "ingles": "Kuwait", "español": "Kuwait" },
        { "ingles": "Kyrgyzstan", "español": "Kirguistán" },
        { "ingles": "Laos", "español": "Laos" },
        { "ingles": "Latvia", "español": "Letonia" },
        { "ingles": "Lebanon", "español": "Líbano" },
        { "ingles": "Lesotho", "español": "Lesoto" },
        { "ingles": "Liberia", "español": "Liberia" },
        { "ingles": "Libya", "español": "Libia" },
        { "ingles": "Liechtenstein", "español": "Liechtenstein" },
        { "ingles": "Lithuania", "español": "Lituania" },
        { "ingles": "Luxembourg", "español": "Luxemburgo" },
        { "ingles": "Macedonia", "español": "Macedonia" },
        { "ingles": "Madagascar", "español": "Madagascar" },
        { "ingles": "Malawi", "español": "Malawi" },
        { "ingles": "Malaysia", "español": "Malasia" },
        { "ingles": "Maldives", "español": "Maldivas" },
        { "ingles": "Mali", "español": "Mali" },
        { "ingles": "Malta", "español": "Malta" },
        { "ingles": "Marshall Islands", "español": "Islas Marshall" },
        { "ingles": "Mauritania", "español": "Mauritania" },
        { "ingles": "Mauritius", "español": "Mauricio" },
        { "ingles": "Mexico", "español": "México" },
        { "ingles": "Micronesia", "español": "Micronesia" },
        { "ingles": "Moldova", "español": "Moldavia" },
        { "ingles": "Monaco", "español": "Mónaco" },
        { "ingles": "Mongolia", "español": "Mongolia" },
        { "ingles": "Montenegro", "español": "Montenegro" },
        { "ingles": "Morocco", "español": "Marruecos" },
        { "ingles": "Mozambique", "español": "Mozambique" },
        { "ingles": "Myanmar", "español": "Myanmar" },
        { "ingles": "Namibia", "español": "Namibia" },
        { "ingles": "Nauru", "español": "Nauru" },
        { "ingles": "Nepal", "español": "Nepal" },
        { "ingles": "Netherlands", "español": "Países Bajos" },
        { "ingles": "New Zealand", "español": "Nueva Zelanda" },
        { "ingles": "Nicaragua", "español": "Nicaragua" },
        { "ingles": "Niger", "español": "Níger" },
        { "ingles": "Nigeria", "español": "Nigeria" },
        { "ingles": "Norway", "español": "Noruega" },
        { "ingles": "Oman", "español": "Omán" },
        { "ingles": "Pakistan", "español": "Pakistán" },
        { "ingles": "Palau", "español": "Palau" },
        { "ingles": "Panama", "español": "Panamá" },
        { "ingles": "Papua New Guinea", "español": "Papúa Nueva Guinea" },
        { "ingles": "Paraguay", "español": "Paraguay" },
        { "ingles": "Peru", "español": "Perú" },
        { "ingles": "Philippines", "español": "Filipinas" },
        { "ingles": "Poland", "español": "Polonia" },
        { "ingles": "Portugal", "español": "Portugal" },
        { "ingles": "Qatar", "español": "Catar" },
        { "ingles": "Romania", "español": "Rumania" },
        { "ingles": "Russia", "español": "Rusia" },
        { "ingles": "Rwanda", "español": "Ruanda" },
        { "ingles": "Saint Kitts and Nevis", "español": "San Cristóbal y Nieves" },
        { "ingles": "Saint Lucia", "español": "Santa Lucía" },
        { "ingles": "Saint Vincent and the Grenadines", "español": "San Vicente y las Granadinas" },
        { "ingles": "Samoa", "español": "Samoa" },
        { "ingles": "San Marino", "español": "San Marino" },
        { "ingles": "Sao Tome and Principe", "español": "Santo Tomé y Príncipe" },
        { "ingles": "Saudi Arabia", "español": "Arabia Saudita" },
        { "ingles": "Senegal", "español": "Senegal" },
        { "ingles": "Serbia", "español": "Serbia" },
        { "ingles": "Seychelles", "español": "Seychelles" },
        { "ingles": "Sierra Leone", "español": "Sierra Leona" },
        { "ingles": "Singapore", "español": "Singapur" },
        { "ingles": "Slovakia", "español": "Eslovaquia" },
        { "ingles": "Slovenia", "español": "Eslovenia" },
        { "ingles": "Solomon Islands", "español": "Islas Salomón" },
        { "ingles": "Somalia", "español": "Somalia" },
        { "ingles": "South Africa", "español": "Sudáfrica" },
        { "ingles": "South Sudan", "español": "Sudán del Sur" },
        { "ingles": "Spain", "español": "España" },
        { "ingles": "Sri Lanka", "español": "Sri Lanka" },
        { "ingles": "Sudan", "español": "Sudán" },
        { "ingles": "Suriingles", "español": "Surinam" },
        { "ingles": "Sweden", "español": "Suecia" },
        { "ingles": "Switzerland", "español": "Suiza" },
        { "ingles": "Syria", "español": "Siria" },
        { "ingles": "Taiwan", "español": "Taiwán" },
        { "ingles": "Tajikistan", "español": "Tayikistán" },
        { "ingles": "Tanzania", "español": "Tanzania" },
        { "ingles": "Thailand", "español": "Tailandia" },
        { "ingles": "Togo", "español": "Togo" },
        { "ingles": "Tonga", "español": "Tonga" },
        { "ingles": "Trinidad and Tobago", "español": "Trinidad y Tobago" },
        { "ingles": "Tunisia", "español": "Túnez" },
        { "ingles": "Turkey", "español": "Turquía" },
        { "ingles": "Turkmenistan", "español": "Turkmenistán" },
        { "ingles": "Tuvalu", "español": "Tuvalu" },
        { "ingles": "Uganda", "español": "Uganda" },
        { "ingles": "Ukraine", "español": "Ucrania" },
        { "ingles": "United Arab Emirates", "español": "Emiratos Árabes Unidos" },
        { "ingles": "United Kingdom", "español": "Reino Unido" },
        { "ingles": "United States", "español": "Estados Unidos" },
        { "ingles": "Uruguay", "español": "Uruguay" },
        { "ingles": "Uzbekistan", "español": "Uzbekistán" },
        { "ingles": "Vanuatu", "español": "Vanuatu" },
        { "ingles": "Vatican City", "español": "Ciudad del Vaticano" },
        { "ingles": "Venezuela", "español": "Venezuela" },
        { "ingles": "Vietnam", "español": "Vietnam" },
        { "ingles": "Yemen", "español": "Yemen" },
        { "ingles": "Zambia", "español": "Zambia" },
        { "ingles": "Zimbabwe", "español": "Zimbabue" }
    ],
    "emociones": [
        { "ingles": "Joy", "español": "Alegría" },
        { "ingles": "Sadness", "español": "Tristeza" },
        { "ingles": "Love", "español": "Amor" },
        { "ingles": "Fear", "español": "Miedo" },
        { "ingles": "Anger", "español": "Enojo" },
        { "ingles": "Surprise", "español": "Sorpresa" },
        { "ingles": "Guilt", "español": "Culpa" },
        { "ingles": "Envy", "español": "Envidia" },
        { "ingles": "Hope", "español": "Esperanza" },
        { "ingles": "Peace", "español": "Paz" },
        { "ingles": "Pride", "español": "Orgullo" },
        { "ingles": "Happiness", "español": "Felicidad" },
        { "ingles": "Disgust", "español": "Asco" },
        { "ingles": "Excitement", "español": "Emoción" },
        { "ingles": "Disappointment", "español": "Decepción" },
        { "ingles": "Anxiety", "español": "Ansiedad" },
        { "ingles": "Relief", "español": "Alivio" },
        { "ingles": "Confusion", "español": "Confusión" },
        { "ingles": "Embarrassment", "español": "Vergüenza" },
        { "ingles": "Jealousy", "español": "Celos" },
        { "ingles": "Curiosity", "español": "Curiosidad" },
        { "ingles": "Grief", "español": "Dolor" },
        { "ingles": "Gratitude", "español": "Gratitud" },
        { "ingles": "Excitement", "español": "Emoción" },
        { "ingles": "Satisfaction", "español": "Satisfacción" },
        { "ingles": "Regret", "español": "Arrepentimiento" },
        { "ingles": "Contentment", "español": "Contentamiento" },
        { "ingles": "Loneliness", "español": "Soledad" },
        { "ingles": "Trust", "español": "Confianza" },
        { "ingles": "Resentment", "español": "Resentimiento" }
    ]
}
    
    
    
    

    
 